daskms/__init__.py
daskms/columns.py
daskms/config.py
daskms/conftest.py
daskms/constants.py
daskms/dask_ms.py
daskms/dataset.py
daskms/dataset_schema.py
daskms/example_data.py
daskms/expressions.py
daskms/fsspec_store.py
daskms/multiton.py
daskms/optimisation.py
daskms/ordering.py
daskms/patterns.py
daskms/query.py
daskms/reads.py
daskms/table.py
daskms/table_executor.py
daskms/table_proxy.py
daskms/table_schemas.py
daskms/testing.py
daskms/utils.py
daskms/writes.py
daskms/apps/__init__.py
daskms/apps/application.py
daskms/apps/conftest.py
daskms/apps/convert.py
daskms/apps/entrypoint.py
daskms/apps/formats.py
daskms/apps/fragments.py
daskms/apps/katdal_import.py
daskms/apps/conf/logging.ini
daskms/apps/tests/test_chunk_transformer.py
daskms/apps/tests/test_convert.py
daskms/descriptors/__init__.py
daskms/descriptors/builder.py
daskms/descriptors/builder_factory.py
daskms/descriptors/ms.py
daskms/descriptors/ms_subtable.py
daskms/descriptors/ratt_ms.py
daskms/descriptors/register_default_builders.py
daskms/descriptors/tests/test_builder_factory.py
daskms/descriptors/tests/test_default_builder.py
daskms/descriptors/tests/test_ms_builder.py
daskms/descriptors/tests/test_ms_subtable_builder.py
daskms/experimental/__init__.py
daskms/experimental/utils.py
daskms/experimental/arrow/__init__.py
daskms/experimental/arrow/arrow_schema.py
daskms/experimental/arrow/extension_types.py
daskms/experimental/arrow/reads.py
daskms/experimental/arrow/require_arrow.py
daskms/experimental/arrow/writes.py
daskms/experimental/arrow/tests/__init__.py
daskms/experimental/arrow/tests/test_extensions.py
daskms/experimental/arrow/tests/test_parquet.py
daskms/experimental/fragments/__init__.py
daskms/experimental/fragments/tests/__init__.py
daskms/experimental/fragments/tests/test_fragments.py
daskms/experimental/katdal/__init__.py
daskms/experimental/katdal/constants.py
daskms/experimental/katdal/corr_products.py
daskms/experimental/katdal/katdal_import.py
dask_ms-0.2.29.dist-info/METADATA
dask_ms-0.2.29.dist-info/WHEEL
dask_ms-0.2.29.dist-info/entry_points.txt
dask_ms-0.2.29.dist-info/licenses/AUTHORS.rst
dask_ms-0.2.29.dist-info/licenses/LICENSE
dask_ms-0.2.29.dist-info/RECORD
