Metadata-Version: 2.4
Name: dask-ms
Version: 0.2.29
Summary: xarray Dataset from CASA Tables
Author-email: Simon Perkins <simon.perkins@gmail.com>
License-Expression: BSD-3-Clause
License-File: AUTHORS.rst
License-File: LICENSE
Requires-Python: <3.14,>=3.10
Requires-Dist: appdirs>=1.4.4
Requires-Dist: cacheout>=0.16.0
Requires-Dist: dask[array]<2024.11.0,>=2023.1.1
Requires-Dist: donfig>=0.8.0
Requires-Dist: fsspec>=2022.7.0
Requires-Dist: numpy>=2.0.0
Requires-Dist: python-casacore>=3.7.0
Provides-Extra: arrow
Requires-Dist: pandas>=2.1.2; extra == 'arrow'
Requires-Dist: pyarrow>=14.0.1; extra == 'arrow'
Provides-Extra: complete
Requires-Dist: katdal>=0.23; extra == 'complete'
Requires-Dist: numcodecs<0.16.0; extra == 'complete'
Requires-Dist: pandas; extra == 'complete'
Requires-Dist: pyarrow>=14.0.1; extra == 'complete'
Requires-Dist: s3fs>=2023.1.0; extra == 'complete'
Requires-Dist: xarray>=2023.01.0; extra == 'complete'
Requires-Dist: zarr<3.0.0,>=2.12.0; extra == 'complete'
Provides-Extra: dev
Requires-Dist: pre-commit>=4.3.0; extra == 'dev'
Requires-Dist: ruff>=0.14.0; extra == 'dev'
Requires-Dist: tbump>=6.11.0; extra == 'dev'
Provides-Extra: docs
Requires-Dist: furo>=2025.9.25; extra == 'docs'
Requires-Dist: numpydoc>=1.9.0; extra == 'docs'
Requires-Dist: pygments>=2.19.2; extra == 'docs'
Requires-Dist: sphinx-copybutton>=0.5.2; extra == 'docs'
Requires-Dist: sphinx>=5.1.1; extra == 'docs'
Provides-Extra: katdal
Requires-Dist: katdal>=0.23; extra == 'katdal'
Requires-Dist: numcodecs<0.16.0; extra == 'katdal'
Requires-Dist: xarray>=2023.01.0; extra == 'katdal'
Requires-Dist: zarr<3.0.0,>=2.12.0; extra == 'katdal'
Provides-Extra: s3
Requires-Dist: s3fs>=2023.1.0; extra == 's3'
Provides-Extra: testing
Requires-Dist: minio>=7.2.0; extra == 'testing'
Requires-Dist: pytest>=8.0.0; extra == 'testing'
Provides-Extra: xarray
Requires-Dist: xarray>=2023.01.0; extra == 'xarray'
Provides-Extra: zarr
Requires-Dist: numcodecs<0.16.0; extra == 'zarr'
Requires-Dist: zarr<3.0.0,>=2.12.0; extra == 'zarr'
